zmq_server/__init__.py
zmq_server/core.py
zmq_server-1.2.0.dist-info/METADATA
zmq_server-1.2.0.dist-info/WHEEL
zmq_server-1.2.0.dist-info/top_level.txt
zmq_server-1.2.0.dist-info/RECORD
