Metadata-Version: 2.4
Name: zmq-server
Version: 1.2.0
Summary: A ZeroMQ based message system with topic subscription, authentication, and heartbeat
Home-page: https://github.com/yourusername/zmq-server
Author: haifeng
Author-email: fenglex@126.com
License: MIT
Keywords: zmq message-system pubsub topic authentication heartbeat
Classifier: Development Status :: 3 - Alpha
Classifier: Intended Audience :: Developers
Classifier: License :: OSI Approved :: MIT License
Classifier: Programming Language :: Python :: 3.8
Classifier: Programming Language :: Python :: 3.9
Classifier: Programming Language :: Python :: 3.10
Classifier: Programming Language :: Python :: 3.11
Classifier: Topic :: Software Development :: Libraries :: Python Modules
Classifier: Topic :: System :: Networking
Requires-Python: >=3.8
Requires-Dist: zmq
Requires-Dist: loguru
Dynamic: author
Dynamic: author-email
Dynamic: classifier
Dynamic: description
Dynamic: description-content-type
Dynamic: home-page
Dynamic: keywords
Dynamic: license
Dynamic: requires-dist
Dynamic: requires-python
Dynamic: summary
